soap_wsse/__init__.py
soap_wsse/ns.py
soap_wsse/signing.py
soap_wsse/suds_plugin.py
soap_wsse-0.2.2.dist-info/DESCRIPTION.rst
soap_wsse-0.2.2.dist-info/METADATA
soap_wsse-0.2.2.dist-info/metadata.json
soap_wsse-0.2.2.dist-info/RECORD
soap_wsse-0.2.2.dist-info/top_level.txt
soap_wsse-0.2.2.dist-info/WHEEL
