Metadata-Version: 2.0
Name: soap-wsse
Version: 0.2.2
Summary: Simply library to sign and verify SOAP XML requests using the
Requires-Dist: dm.xmlsec.binding (==1.3.2)
Requires-Dist: lxml (>=3.0.0)
Requires-Dist: pyOpenSSL (>=0.14)
Provides-Extra: test
Requires-Dist: pytest (>=2.6.0); extra == 'test'
Requires-Dist: pytest-cov (>=1.7.0); extra == 'test'
Requires-Dist: pretend (>=1.0.0); extra == 'test'
Requires-Dist: suds-jurko (>=0.6); extra == 'test'
